autodistill_clip/__init__.py
autodistill_clip/clip_model.py
autodistill_clip-0.1.5.dist-info/LICENSE.md
autodistill_clip-0.1.5.dist-info/METADATA
autodistill_clip-0.1.5.dist-info/WHEEL
autodistill_clip-0.1.5.dist-info/top_level.txt
autodistill_clip-0.1.5.dist-info/RECORD
