Metadata-Version: 2.1
Name: autodistill-clip
Version: 0.1.5
Summary: CLIP module for use with Autodistill
Home-page: https://github.com/autodistill/autodistill-clip
Author: Roboflow
Author-email: support@roboflow.com
Classifier: Programming Language :: Python :: 3
Classifier: License :: OSI Approved :: MIT License
Classifier: Operating System :: OS Independent
Requires-Python: >=3.7
License-File: LICENSE.md
Requires-Dist: torch
Requires-Dist: supervision
Requires-Dist: numpy
Requires-Dist: rf-clip
Provides-Extra: dev
Requires-Dist: flake8 ; extra == 'dev'
Requires-Dist: black ==22.3.0 ; extra == 'dev'
Requires-Dist: isort ; extra == 'dev'
Requires-Dist: twine ; extra == 'dev'
Requires-Dist: pytest ; extra == 'dev'
Requires-Dist: wheel ; extra == 'dev'
